{
    "0": [
        "data",
        "marketing",
        "diversity",
        "niq",
        "bcg",
        "courses",
        "shift",
        "global",
        "technology",
        "experience",
        "science",
        "business",
        "analytics",
        "protected",
        "information"
    ],
    "1": [
        "ia",
        "modelos",
        "soluções",
        "ciência",
        "desenvolvimento",
        "projetos",
        "estatística",
        "inteligência",
        "learning",
        "negócio",
        "artificial",
        "algoritmos",
        "machine",
        "conhecimento",
        "bibliotecas"
    ],
    "2": [
        "pessoas",
        "análise",
        "soluções",
        "experian",
        "modelos",
        "negócios",
        "porto",
        "learning",
        "prevenção",
        "vida",
        "clientes",
        "seguro",
        "modelagem",
        "áreas",
        "ambiente"
    ],
    "3": [
        "operacionais",
        "vale",
        "ferramentas",
        "processos",
        "kpis",
        "jr",
        "fraude",
        "acordo",
        "dashboards",
        "escala",
        "negócio",
        "conhecimento",
        "dentro",
        "grandes",
        "regras"
    ],
    "4": [
        "ai",
        "data",
        "experience",
        "h2o",
        "product",
        "work",
        "customer",
        "science",
        "solutions",
        "using",
        "team",
        "business",
        "engineering",
        "cloud",
        "analytics"
    ]
}