{
    "0": [
        "data",
        "experience",
        "team",
        "science",
        "business",
        "research",
        "work",
        "product",
        "spatial",
        "cloudwalk",
        "shift",
        "us",
        "models",
        "new",
        "building"
    ],
    "1": [
        "bradesco",
        "produtos",
        "crédito",
        "empresas",
        "adesão",
        "opcional",
        "condições",
        "bem",
        "pricing",
        "rentabilidade",
        "financeiros",
        "pessoas",
        "specialist",
        "sustentável",
        "carteira"
    ],
    "2": [
        "artefact",
        "empatia",
        "equipe",
        "cadeia",
        "compartilhamento",
        "juntará",
        "quiser",
        "conhecimento",
        "pode",
        "trabalhará",
        "clientes",
        "soluções",
        "cientistas",
        "valor",
        "office"
    ],
    "3": [
        "ia",
        "modelos",
        "soluções",
        "desenvolvimento",
        "projetos",
        "ferramentas",
        "áreas",
        "cientista",
        "linguagem",
        "conhecimento",
        "sistemas",
        "negócio",
        "learning",
        "machine",
        "engenharia"
    ],
    "4": [
        "modelos",
        "crédito",
        "pessoas",
        "learning",
        "conhecimento",
        "resultados",
        "machine",
        "vale",
        "estatística",
        "análise",
        "vida",
        "modelagem",
        "soluções",
        "auxílio",
        "preditivos"
    ]
}